{
  "status": 200,
  "message": "OK",
  "data": [
    {
      "FlightSegment": [
        {
          "BookingClassAvail": [
            {
              "Availability": "7",
              "BrandID": null,
              "ResBookDesigCode": "J",
              "RPH": "1",
              "AggregatedContent": false,
              "AggregatedContentSpecified": true
            },
            {
              "Availability": "7",
              "BrandID": null,
              "ResBookDesigCode": "C",
              "RPH": "2",
              "AggregatedContent": false,
              "AggregatedContentSpecified": true
            },
            {
              "Availability": "6",
              "BrandID": null,
              "ResBookDesigCode": "D",
              "RPH": "3",
              "AggregatedContent": false,
              "AggregatedContentSpecified": true
            },
            {
              "Availability": "0",
              "BrandID": null,
              "ResBookDesigCode": "I",
              "RPH": "4",
              "AggregatedContent": false,
              "AggregatedContentSpecified": true
            },
            {
              "Availability": "0",
              "BrandID": null,
              "ResBookDesigCode": "O",
              "RPH": "5",
              "AggregatedContent": false,
              "AggregatedContentSpecified": true
            },
            {
              "Availability": "7",
              "BrandID": null,
              "ResBookDesigCode": "Y",
              "RPH": "6",
              "AggregatedContent": false,
              "AggregatedContentSpecified": true
            },
            {
              "Availability": "7",
              "BrandID": null,
              "ResBookDesigCode": "B",
              "RPH": "7",
              "AggregatedContent": false,
              "AggregatedContentSpecified": true
            },
            {
              "Availability": "7",
              "BrandID": null,
              "ResBookDesigCode": "M",
              "RPH": "8",
              "AggregatedContent": false,
              "AggregatedContentSpecified": true
            },
            {
              "Availability": "7",
              "BrandID": null,
              "ResBookDesigCode": "S",
              "RPH": "9",
              "AggregatedContent": false,
              "AggregatedContentSpecified": true
            },
            {
              "Availability": "7",
              "BrandID": null,
              "ResBookDesigCode": "H",
              "RPH": "10",
              "AggregatedContent": false,
              "AggregatedContentSpecified": true
            },
            {
              "Availability": "7",
              "BrandID": null,
              "ResBookDesigCode": "K",
              "RPH": "11",
              "AggregatedContent": false,
              "AggregatedContentSpecified": true
            },
            {
              "Availability": "7",
              "BrandID": null,
              "ResBookDesigCode": "L",
              "RPH": "12",
              "AggregatedContent": false,
              "AggregatedContentSpecified": true
            },
            {
              "Availability": "7",
              "BrandID": null,
              "ResBookDesigCode": "Q",
              "RPH": "13",
              "AggregatedContent": false,
              "AggregatedContentSpecified": true
            },
            {
              "Availability": "7",
              "BrandID": null,
              "ResBookDesigCode": "N",
              "RPH": "14",
              "AggregatedContent": false,
              "AggregatedContentSpecified": true
            },
            {
              "Availability": "7",
              "BrandID": null,
              "ResBookDesigCode": "R",
              "RPH": "15",
              "AggregatedContent": false,
              "AggregatedContentSpecified": true
            },
            {
              "Availability": "7",
              "BrandID": null,
              "ResBookDesigCode": "T",
              "RPH": "16",
              "AggregatedContent": false,
              "AggregatedContentSpecified": true
            },
            {
              "Availability": "7",
              "BrandID": null,
              "ResBookDesigCode": "E",
              "RPH": "17",
              "AggregatedContent": false,
              "AggregatedContentSpecified": true
            },
            {
              "Availability": "0",
              "BrandID": null,
              "ResBookDesigCode": "A",
              "RPH": "18",
              "AggregatedContent": false,
              "AggregatedContentSpecified": true
            },
            {
              "Availability": "7",
              "BrandID": null,
              "ResBookDesigCode": "P",
              "RPH": "19",
              "AggregatedContent": false,
              "AggregatedContentSpecified": true
            },
            {
              "Availability": "3",
              "BrandID": null,
              "ResBookDesigCode": "X",
              "RPH": "20",
              "AggregatedContent": false,
              "AggregatedContentSpecified": true
            },
            {
              "Availability": "0",
              "BrandID": null,
              "ResBookDesigCode": "V",
              "RPH": "21",
              "AggregatedContent": false,
              "AggregatedContentSpecified": true
            }
          ],
          "DaysOfOperation": {
            "OperationSchedule": {
              "OperationTimes": {
                "OperationTime": {
                  "Fri": true,
                  "FriSpecified": true,
                  "Mon": true,
                  "MonSpecified": true,
                  "Sat": true,
                  "SatSpecified": true,
                  "Sun": true,
                  "SunSpecified": true,
                  "Thur": true,
                  "ThurSpecified": true,
                  "Tue": true,
                  "TueSpecified": true,
                  "Weds": true,
                  "WedsSpecified": true
                }
              }
            }
          },
          "DestinationLocation": {
            "LocationCode": "SGN"
          },
          "DisclosureAirline": null,
          "Equipment": {
            "AirEquipType": "321"
          },
          "FlightDetails": {
            "Text": null,
            "Canceled": false,
            "CanceledSpecified": true,
            "Charter": false,
            "CharterSpecified": true,
            "CodeshareBlockDisplay": null,
            "DiscontinueDate": null,
            "EffectiveDate": null,
            "GroundTime": "0",
            "TotalTravelTime": "135",
            "TrafficRestrictionCode": null
          },
          "MarketingAirline": {
            "Code": "VN",
            "FlightNumber": "233",
            "ParticipationLevel": null
          },
          "Meal": [
            {
              "MealCode": "L"
            }
          ],
          "OperatingAirline": null,
          "OriginLocation": {
            "LocationCode": "HAN"
          },
          "ArrivalDateTime": "08-25T07:15",
          "ConnectionInd": null,
          "DepartureDateTime": "08-25T05:00",
          "DOT_Ind": "N",
          "eTicket": true,
          "eTicketSpecified": true,
          "FlightNumber": "233",
          "OnTimeInd": null,
          "RPH": "1",
          "SmokingAllowed": false,
          "SmokingAllowedSpecified": true,
          "StopQuantity": "0"
        }
      ],
      "RPH": "1"
    },
    {
      "FlightSegment": [
        {
          "BookingClassAvail": [
            {
              "Availability": "7",
              "BrandID": null,
              "ResBookDesigCode": "J",
              "RPH": "1",
              "AggregatedContent": false,
              "AggregatedContentSpecified": true
            },
            {
              "Availability": "7",
              "BrandID": null,
              "ResBookDesigCode": "C",
              "RPH": "2",
              "AggregatedContent": false,
              "AggregatedContentSpecified": true
            },
            {
              "Availability": "6",
              "BrandID": null,
              "ResBookDesigCode": "D",
              "RPH": "3",
              "AggregatedContent": false,
              "AggregatedContentSpecified": true
            },
            {
              "Availability": "0",
              "BrandID": null,
              "ResBookDesigCode": "I",
              "RPH": "4",
              "AggregatedContent": false,
              "AggregatedContentSpecified": true
            },
            {
              "Availability": "0",
              "BrandID": null,
              "ResBookDesigCode": "O",
              "RPH": "5",
              "AggregatedContent": false,
              "AggregatedContentSpecified": true
            },
            {
              "Availability": "7",
              "BrandID": null,
              "ResBookDesigCode": "Y",
              "RPH": "6",
              "AggregatedContent": false,
              "AggregatedContentSpecified": true
            },
            {
              "Availability": "7",
              "BrandID": null,
              "ResBookDesigCode": "B",
              "RPH": "7",
              "AggregatedContent": false,
              "AggregatedContentSpecified": true
            },
            {
              "Availability": "7",
              "BrandID": null,
              "ResBookDesigCode": "M",
              "RPH": "8",
              "AggregatedContent": false,
              "AggregatedContentSpecified": true
            },
            {
              "Availability": "7",
              "BrandID": null,
              "ResBookDesigCode": "S",
              "RPH": "9",
              "AggregatedContent": false,
              "AggregatedContentSpecified": true
            },
            {
              "Availability": "7",
              "BrandID": null,
              "ResBookDesigCode": "H",
              "RPH": "10",
              "AggregatedContent": false,
              "AggregatedContentSpecified": true
            },
            {
              "Availability": "7",
              "BrandID": null,
              "ResBookDesigCode": "K",
              "RPH": "11",
              "AggregatedContent": false,
              "AggregatedContentSpecified": true
            },
            {
              "Availability": "7",
              "BrandID": null,
              "ResBookDesigCode": "L",
              "RPH": "12",
              "AggregatedContent": false,
              "AggregatedContentSpecified": true
            },
            {
              "Availability": "7",
              "BrandID": null,
              "ResBookDesigCode": "Q",
              "RPH": "13",
              "AggregatedContent": false,
              "AggregatedContentSpecified": true
            },
            {
              "Availability": "7",
              "BrandID": null,
              "ResBookDesigCode": "N",
              "RPH": "14",
              "AggregatedContent": false,
              "AggregatedContentSpecified": true
            },
            {
              "Availability": "7",
              "BrandID": null,
              "ResBookDesigCode": "R",
              "RPH": "15",
              "AggregatedContent": false,
              "AggregatedContentSpecified": true
            },
            {
              "Availability": "7",
              "BrandID": null,
              "ResBookDesigCode": "T",
              "RPH": "16",
              "AggregatedContent": false,
              "AggregatedContentSpecified": true
            },
            {
              "Availability": "7",
              "BrandID": null,
              "ResBookDesigCode": "E",
              "RPH": "17",
              "AggregatedContent": false,
              "AggregatedContentSpecified": true
            },
            {
              "Availability": "0",
              "BrandID": null,
              "ResBookDesigCode": "A",
              "RPH": "18",
              "AggregatedContent": false,
              "AggregatedContentSpecified": true
            },
            {
              "Availability": "7",
              "BrandID": null,
              "ResBookDesigCode": "P",
              "RPH": "19",
              "AggregatedContent": false,
              "AggregatedContentSpecified": true
            },
            {
              "Availability": "3",
              "BrandID": null,
              "ResBookDesigCode": "X",
              "RPH": "20",
              "AggregatedContent": false,
              "AggregatedContentSpecified": true
            },
            {
              "Availability": "0",
              "BrandID": null,
              "ResBookDesigCode": "V",
              "RPH": "21",
              "AggregatedContent": false,
              "AggregatedContentSpecified": true
            }
          ],
          "DaysOfOperation": {
            "OperationSchedule": {
              "OperationTimes": {
                "OperationTime": {
                  "Fri": true,
                  "FriSpecified": true,
                  "Mon": false,
                  "MonSpecified": true,
                  "Sat": false,
                  "SatSpecified": true,
                  "Sun": true,
                  "SunSpecified": true,
                  "Thur": false,
                  "ThurSpecified": true,
                  "Tue": true,
                  "TueSpecified": true,
                  "Weds": true,
                  "WedsSpecified": true
                }
              }
            }
          },
          "DestinationLocation": {
            "LocationCode": "SGN"
          },
          "DisclosureAirline": null,
          "Equipment": {
            "AirEquipType": "321"
          },
          "FlightDetails": {
            "Text": null,
            "Canceled": false,
            "CanceledSpecified": true,
            "Charter": false,
            "CharterSpecified": true,
            "CodeshareBlockDisplay": null,
            "DiscontinueDate": null,
            "EffectiveDate": null,
            "GroundTime": "0",
            "TotalTravelTime": "135",
            "TrafficRestrictionCode": null
          },
          "MarketingAirline": {
            "Code": "VN",
            "FlightNumber": "235",
            "ParticipationLevel": null
          },
          "Meal": [
            {
              "MealCode": "B"
            },
            {
              "MealCode": "S"
            }
          ],
          "OperatingAirline": null,
          "OriginLocation": {
            "LocationCode": "HAN"
          },
          "ArrivalDateTime": "08-25T07:45",
          "ConnectionInd": null,
          "DepartureDateTime": "08-25T05:30",
          "DOT_Ind": "N",
          "eTicket": true,
          "eTicketSpecified": true,
          "FlightNumber": "235",
          "OnTimeInd": null,
          "RPH": "2",
          "SmokingAllowed": false,
          "SmokingAllowedSpecified": true,
          "StopQuantity": "0"
        }
      ],
      "RPH": "2"
    },
    {
      "FlightSegment": [
        {
          "BookingClassAvail": [
            {
              "Availability": "7",
              "BrandID": null,
              "ResBookDesigCode": "J",
              "RPH": "1",
              "AggregatedContent": false,
              "AggregatedContentSpecified": true
            },
            {
              "Availability": "7",
              "BrandID": null,
              "ResBookDesigCode": "C",
              "RPH": "2",
              "AggregatedContent": false,
              "AggregatedContentSpecified": true
            },
            {
              "Availability": "6",
              "BrandID": null,
              "ResBookDesigCode": "D",
              "RPH": "3",
              "AggregatedContent": false,
              "AggregatedContentSpecified": true
            },
            {
              "Availability": "0",
              "BrandID": null,
              "ResBookDesigCode": "I",
              "RPH": "4",
              "AggregatedContent": false,
              "AggregatedContentSpecified": true
            },
            {
              "Availability": "0",
              "BrandID": null,
              "ResBookDesigCode": "O",
              "RPH": "5",
              "AggregatedContent": false,
              "AggregatedContentSpecified": true
            },
            {
              "Availability": "7",
              "BrandID": null,
              "ResBookDesigCode": "Y",
              "RPH": "6",
              "AggregatedContent": false,
              "AggregatedContentSpecified": true
            },
            {
              "Availability": "7",
              "BrandID": null,
              "ResBookDesigCode": "B",
              "RPH": "7",
              "AggregatedContent": false,
              "AggregatedContentSpecified": true
            },
            {
              "Availability": "7",
              "BrandID": null,
              "ResBookDesigCode": "M",
              "RPH": "8",
              "AggregatedContent": false,
              "AggregatedContentSpecified": true
            },
            {
              "Availability": "7",
              "BrandID": null,
              "ResBookDesigCode": "S",
              "RPH": "9",
              "AggregatedContent": false,
              "AggregatedContentSpecified": true
            },
            {
              "Availability": "7",
              "BrandID": null,
              "ResBookDesigCode": "H",
              "RPH": "10",
              "AggregatedContent": false,
              "AggregatedContentSpecified": true
            },
            {
              "Availability": "7",
              "BrandID": null,
              "ResBookDesigCode": "K",
              "RPH": "11",
              "AggregatedContent": false,
              "AggregatedContentSpecified": true
            },
            {
              "Availability": "7",
              "BrandID": null,
              "ResBookDesigCode": "L",
              "RPH": "12",
              "AggregatedContent": false,
              "AggregatedContentSpecified": true
            },
            {
              "Availability": "7",
              "BrandID": null,
              "ResBookDesigCode": "Q",
              "RPH": "13",
              "AggregatedContent": false,
              "AggregatedContentSpecified": true
            },
            {
              "Availability": "7",
              "BrandID": null,
              "ResBookDesigCode": "N",
              "RPH": "14",
              "AggregatedContent": false,
              "AggregatedContentSpecified": true
            },
            {
              "Availability": "7",
              "BrandID": null,
              "ResBookDesigCode": "R",
              "RPH": "15",
              "AggregatedContent": false,
              "AggregatedContentSpecified": true
            },
            {
              "Availability": "7",
              "BrandID": null,
              "ResBookDesigCode": "T",
              "RPH": "16",
              "AggregatedContent": false,
              "AggregatedContentSpecified": true
            },
            {
              "Availability": "7",
              "BrandID": null,
              "ResBookDesigCode": "E",
              "RPH": "17",
              "AggregatedContent": false,
              "AggregatedContentSpecified": true
            },
            {
              "Availability": "0",
              "BrandID": null,
              "ResBookDesigCode": "A",
              "RPH": "18",
              "AggregatedContent": false,
              "AggregatedContentSpecified": true
            },
            {
              "Availability": "7",
              "BrandID": null,
              "ResBookDesigCode": "P",
              "RPH": "19",
              "AggregatedContent": false,
              "AggregatedContentSpecified": true
            },
            {
              "Availability": "3",
              "BrandID": null,
              "ResBookDesigCode": "X",
              "RPH": "20",
              "AggregatedContent": false,
              "AggregatedContentSpecified": true
            },
            {
              "Availability": "0",
              "BrandID": null,
              "ResBookDesigCode": "V",
              "RPH": "21",
              "AggregatedContent": false,
              "AggregatedContentSpecified": true
            }
          ],
          "DaysOfOperation": {
            "OperationSchedule": {
              "OperationTimes": {
                "OperationTime": {
                  "Fri": true,
                  "FriSpecified": true,
                  "Mon": true,
                  "MonSpecified": true,
                  "Sat": true,
                  "SatSpecified": true,
                  "Sun": true,
                  "SunSpecified": true,
                  "Thur": true,
                  "ThurSpecified": true,
                  "Tue": true,
                  "TueSpecified": true,
                  "Weds": true,
                  "WedsSpecified": true
                }
              }
            }
          },
          "DestinationLocation": {
            "LocationCode": "SGN"
          },
          "DisclosureAirline": null,
          "Equipment": {
            "AirEquipType": "321"
          },
          "FlightDetails": {
            "Text": null,
            "Canceled": false,
            "CanceledSpecified": true,
            "Charter": false,
            "CharterSpecified": true,
            "CodeshareBlockDisplay": null,
            "DiscontinueDate": null,
            "EffectiveDate": null,
            "GroundTime": "0",
            "TotalTravelTime": "135",
            "TrafficRestrictionCode": null
          },
          "MarketingAirline": {
            "Code": "VN",
            "FlightNumber": "237",
            "ParticipationLevel": null
          },
          "Meal": [
            {
              "MealCode": "B"
            },
            {
              "MealCode": "S"
            }
          ],
          "OperatingAirline": null,
          "OriginLocation": {
            "LocationCode": "HAN"
          },
          "ArrivalDateTime": "08-25T08:15",
          "ConnectionInd": null,
          "DepartureDateTime": "08-25T06:00",
          "DOT_Ind": "N",
          "eTicket": true,
          "eTicketSpecified": true,
          "FlightNumber": "237",
          "OnTimeInd": null,
          "RPH": "3",
          "SmokingAllowed": false,
          "SmokingAllowedSpecified": true,
          "StopQuantity": "0"
        }
      ],
      "RPH": "3"
    },
    {
      "FlightSegment": [
        {
          "BookingClassAvail": [
            {
              "Availability": "7",
              "BrandID": null,
              "ResBookDesigCode": "J",
              "RPH": "1",
              "AggregatedContent": false,
              "AggregatedContentSpecified": true
            },
            {
              "Availability": "7",
              "BrandID": null,
              "ResBookDesigCode": "C",
              "RPH": "2",
              "AggregatedContent": false,
              "AggregatedContentSpecified": true
            },
            {
              "Availability": "7",
              "BrandID": null,
              "ResBookDesigCode": "D",
              "RPH": "3",
              "AggregatedContent": false,
              "AggregatedContentSpecified": true
            },
            {
              "Availability": "0",
              "BrandID": null,
              "ResBookDesigCode": "I",
              "RPH": "4",
              "AggregatedContent": false,
              "AggregatedContentSpecified": true
            },
            {
              "Availability": "5",
              "BrandID": null,
              "ResBookDesigCode": "O",
              "RPH": "5",
              "AggregatedContent": false,
              "AggregatedContentSpecified": true
            },
            {
              "Availability": "7",
              "BrandID": null,
              "ResBookDesigCode": "Y",
              "RPH": "6",
              "AggregatedContent": false,
              "AggregatedContentSpecified": true
            },
            {
              "Availability": "7",
              "BrandID": null,
              "ResBookDesigCode": "B",
              "RPH": "7",
              "AggregatedContent": false,
              "AggregatedContentSpecified": true
            },
            {
              "Availability": "7",
              "BrandID": null,
              "ResBookDesigCode": "M",
              "RPH": "8",
              "AggregatedContent": false,
              "AggregatedContentSpecified": true
            },
            {
              "Availability": "7",
              "BrandID": null,
              "ResBookDesigCode": "S",
              "RPH": "9",
              "AggregatedContent": false,
              "AggregatedContentSpecified": true
            },
            {
              "Availability": "7",
              "BrandID": null,
              "ResBookDesigCode": "H",
              "RPH": "10",
              "AggregatedContent": false,
              "AggregatedContentSpecified": true
            },
            {
              "Availability": "7",
              "BrandID": null,
              "ResBookDesigCode": "K",
              "RPH": "11",
              "AggregatedContent": false,
              "AggregatedContentSpecified": true
            },
            {
              "Availability": "7",
              "BrandID": null,
              "ResBookDesigCode": "L",
              "RPH": "12",
              "AggregatedContent": false,
              "AggregatedContentSpecified": true
            },
            {
              "Availability": "7",
              "BrandID": null,
              "ResBookDesigCode": "Q",
              "RPH": "13",
              "AggregatedContent": false,
              "AggregatedContentSpecified": true
            },
            {
              "Availability": "7",
              "BrandID": null,
              "ResBookDesigCode": "N",
              "RPH": "14",
              "AggregatedContent": false,
              "AggregatedContentSpecified": true
            },
            {
              "Availability": "7",
              "BrandID": null,
              "ResBookDesigCode": "R",
              "RPH": "15",
              "AggregatedContent": false,
              "AggregatedContentSpecified": true
            },
            {
              "Availability": "7",
              "BrandID": null,
              "ResBookDesigCode": "T",
              "RPH": "16",
              "AggregatedContent": false,
              "AggregatedContentSpecified": true
            },
            {
              "Availability": "7",
              "BrandID": null,
              "ResBookDesigCode": "E",
              "RPH": "17",
              "AggregatedContent": false,
              "AggregatedContentSpecified": true
            },
            {
              "Availability": "0",
              "BrandID": null,
              "ResBookDesigCode": "A",
              "RPH": "18",
              "AggregatedContent": false,
              "AggregatedContentSpecified": true
            },
            {
              "Availability": "7",
              "BrandID": null,
              "ResBookDesigCode": "P",
              "RPH": "19",
              "AggregatedContent": false,
              "AggregatedContentSpecified": true
            },
            {
              "Availability": "3",
              "BrandID": null,
              "ResBookDesigCode": "X",
              "RPH": "20",
              "AggregatedContent": false,
              "AggregatedContentSpecified": true
            },
            {
              "Availability": "0",
              "BrandID": null,
              "ResBookDesigCode": "V",
              "RPH": "21",
              "AggregatedContent": false,
              "AggregatedContentSpecified": true
            }
          ],
          "DaysOfOperation": {
            "OperationSchedule": {
              "OperationTimes": {
                "OperationTime": {
                  "Fri": true,
                  "FriSpecified": true,
                  "Mon": true,
                  "MonSpecified": true,
                  "Sat": true,
                  "SatSpecified": true,
                  "Sun": true,
                  "SunSpecified": true,
                  "Thur": true,
                  "ThurSpecified": true,
                  "Tue": true,
                  "TueSpecified": true,
                  "Weds": true,
                  "WedsSpecified": true
                }
              }
            }
          },
          "DestinationLocation": {
            "LocationCode": "SGN"
          },
          "DisclosureAirline": null,
          "Equipment": {
            "AirEquipType": "787"
          },
          "FlightDetails": {
            "Text": null,
            "Canceled": false,
            "CanceledSpecified": true,
            "Charter": false,
            "CharterSpecified": true,
            "CodeshareBlockDisplay": null,
            "DiscontinueDate": null,
            "EffectiveDate": null,
            "GroundTime": "0",
            "TotalTravelTime": "135",
            "TrafficRestrictionCode": null
          },
          "MarketingAirline": {
            "Code": "VN",
            "FlightNumber": "207",
            "ParticipationLevel": null
          },
          "Meal": [
            {
              "MealCode": "B"
            },
            {
              "MealCode": "S"
            }
          ],
          "OperatingAirline": null,
          "OriginLocation": {
            "LocationCode": "HAN"
          },
          "ArrivalDateTime": "08-25T09:15",
          "ConnectionInd": null,
          "DepartureDateTime": "08-25T07:00",
          "DOT_Ind": "N",
          "eTicket": true,
          "eTicketSpecified": true,
          "FlightNumber": "207",
          "OnTimeInd": null,
          "RPH": "4",
          "SmokingAllowed": false,
          "SmokingAllowedSpecified": true,
          "StopQuantity": "0"
        }
      ],
      "RPH": "4"
    },
    {
      "FlightSegment": [
        {
          "BookingClassAvail": [
            {
              "Availability": "7",
              "BrandID": null,
              "ResBookDesigCode": "J",
              "RPH": "1",
              "AggregatedContent": false,
              "AggregatedContentSpecified": true
            },
            {
              "Availability": "7",
              "BrandID": null,
              "ResBookDesigCode": "C",
              "RPH": "2",
              "AggregatedContent": false,
              "AggregatedContentSpecified": true
            },
            {
              "Availability": "7",
              "BrandID": null,
              "ResBookDesigCode": "D",
              "RPH": "3",
              "AggregatedContent": false,
              "AggregatedContentSpecified": true
            },
            {
              "Availability": "0",
              "BrandID": null,
              "ResBookDesigCode": "I",
              "RPH": "4",
              "AggregatedContent": false,
              "AggregatedContentSpecified": true
            },
            {
              "Availability": "5",
              "BrandID": null,
              "ResBookDesigCode": "O",
              "RPH": "5",
              "AggregatedContent": false,
              "AggregatedContentSpecified": true
            },
            {
              "Availability": "7",
              "BrandID": null,
              "ResBookDesigCode": "Y",
              "RPH": "6",
              "AggregatedContent": false,
              "AggregatedContentSpecified": true
            },
            {
              "Availability": "7",
              "BrandID": null,
              "ResBookDesigCode": "B",
              "RPH": "7",
              "AggregatedContent": false,
              "AggregatedContentSpecified": true
            },
            {
              "Availability": "7",
              "BrandID": null,
              "ResBookDesigCode": "M",
              "RPH": "8",
              "AggregatedContent": false,
              "AggregatedContentSpecified": true
            },
            {
              "Availability": "7",
              "BrandID": null,
              "ResBookDesigCode": "S",
              "RPH": "9",
              "AggregatedContent": false,
              "AggregatedContentSpecified": true
            },
            {
              "Availability": "7",
              "BrandID": null,
              "ResBookDesigCode": "H",
              "RPH": "10",
              "AggregatedContent": false,
              "AggregatedContentSpecified": true
            },
            {
              "Availability": "7",
              "BrandID": null,
              "ResBookDesigCode": "K",
              "RPH": "11",
              "AggregatedContent": false,
              "AggregatedContentSpecified": true
            },
            {
              "Availability": "7",
              "BrandID": null,
              "ResBookDesigCode": "L",
              "RPH": "12",
              "AggregatedContent": false,
              "AggregatedContentSpecified": true
            },
            {
              "Availability": "7",
              "BrandID": null,
              "ResBookDesigCode": "Q",
              "RPH": "13",
              "AggregatedContent": false,
              "AggregatedContentSpecified": true
            },
            {
              "Availability": "7",
              "BrandID": null,
              "ResBookDesigCode": "N",
              "RPH": "14",
              "AggregatedContent": false,
              "AggregatedContentSpecified": true
            },
            {
              "Availability": "7",
              "BrandID": null,
              "ResBookDesigCode": "R",
              "RPH": "15",
              "AggregatedContent": false,
              "AggregatedContentSpecified": true
            },
            {
              "Availability": "7",
              "BrandID": null,
              "ResBookDesigCode": "T",
              "RPH": "16",
              "AggregatedContent": false,
              "AggregatedContentSpecified": true
            },
            {
              "Availability": "7",
              "BrandID": null,
              "ResBookDesigCode": "E",
              "RPH": "17",
              "AggregatedContent": false,
              "AggregatedContentSpecified": true
            },
            {
              "Availability": "0",
              "BrandID": null,
              "ResBookDesigCode": "A",
              "RPH": "18",
              "AggregatedContent": false,
              "AggregatedContentSpecified": true
            },
            {
              "Availability": "7",
              "BrandID": null,
              "ResBookDesigCode": "P",
              "RPH": "19",
              "AggregatedContent": false,
              "AggregatedContentSpecified": true
            },
            {
              "Availability": "3",
              "BrandID": null,
              "ResBookDesigCode": "X",
              "RPH": "20",
              "AggregatedContent": false,
              "AggregatedContentSpecified": true
            },
            {
              "Availability": "0",
              "BrandID": null,
              "ResBookDesigCode": "V",
              "RPH": "21",
              "AggregatedContent": false,
              "AggregatedContentSpecified": true
            }
          ],
          "DaysOfOperation": {
            "OperationSchedule": {
              "OperationTimes": {
                "OperationTime": {
                  "Fri": true,
                  "FriSpecified": true,
                  "Mon": true,
                  "MonSpecified": true,
                  "Sat": true,
                  "SatSpecified": true,
                  "Sun": true,
                  "SunSpecified": true,
                  "Thur": true,
                  "ThurSpecified": true,
                  "Tue": true,
                  "TueSpecified": true,
                  "Weds": true,
                  "WedsSpecified": true
                }
              }
            }
          },
          "DestinationLocation": {
            "LocationCode": "SGN"
          },
          "DisclosureAirline": null,
          "Equipment": {
            "AirEquipType": "359"
          },
          "FlightDetails": {
            "Text": null,
            "Canceled": false,
            "CanceledSpecified": true,
            "Charter": false,
            "CharterSpecified": true,
            "CodeshareBlockDisplay": null,
            "DiscontinueDate": null,
            "EffectiveDate": null,
            "GroundTime": "0",
            "TotalTravelTime": "135",
            "TrafficRestrictionCode": null
          },
          "MarketingAirline": {
            "Code": "VN",
            "FlightNumber": "243",
            "ParticipationLevel": null
          },
          "Meal": [
            {
              "MealCode": "S"
            }
          ],
          "OperatingAirline": null,
          "OriginLocation": {
            "LocationCode": "HAN"
          },
          "ArrivalDateTime": "08-25T10:15",
          "ConnectionInd": null,
          "DepartureDateTime": "08-25T08:00",
          "DOT_Ind": "N",
          "eTicket": true,
          "eTicketSpecified": true,
          "FlightNumber": "243",
          "OnTimeInd": null,
          "RPH": "5",
          "SmokingAllowed": false,
          "SmokingAllowedSpecified": true,
          "StopQuantity": "0"
        }
      ],
      "RPH": "5"
    },
    {
      "FlightSegment": [
        {
          "BookingClassAvail": [
            {
              "Availability": "7",
              "BrandID": null,
              "ResBookDesigCode": "J",
              "RPH": "1",
              "AggregatedContent": false,
              "AggregatedContentSpecified": true
            },
            {
              "Availability": "7",
              "BrandID": null,
              "ResBookDesigCode": "C",
              "RPH": "2",
              "AggregatedContent": false,
              "AggregatedContentSpecified": true
            },
            {
              "Availability": "7",
              "BrandID": null,
              "ResBookDesigCode": "D",
              "RPH": "3",
              "AggregatedContent": false,
              "AggregatedContentSpecified": true
            },
            {
              "Availability": "0",
              "BrandID": null,
              "ResBookDesigCode": "I",
              "RPH": "4",
              "AggregatedContent": false,
              "AggregatedContentSpecified": true
            },
            {
              "Availability": "5",
              "BrandID": null,
              "ResBookDesigCode": "O",
              "RPH": "5",
              "AggregatedContent": false,
              "AggregatedContentSpecified": true
            },
            {
              "Availability": "7",
              "BrandID": null,
              "ResBookDesigCode": "Y",
              "RPH": "6",
              "AggregatedContent": false,
              "AggregatedContentSpecified": true
            },
            {
              "Availability": "7",
              "BrandID": null,
              "ResBookDesigCode": "B",
              "RPH": "7",
              "AggregatedContent": false,
              "AggregatedContentSpecified": true
            },
            {
              "Availability": "7",
              "BrandID": null,
              "ResBookDesigCode": "M",
              "RPH": "8",
              "AggregatedContent": false,
              "AggregatedContentSpecified": true
            },
            {
              "Availability": "7",
              "BrandID": null,
              "ResBookDesigCode": "S",
              "RPH": "9",
              "AggregatedContent": false,
              "AggregatedContentSpecified": true
            },
            {
              "Availability": "7",
              "BrandID": null,
              "ResBookDesigCode": "H",
              "RPH": "10",
              "AggregatedContent": false,
              "AggregatedContentSpecified": true
            },
            {
              "Availability": "7",
              "BrandID": null,
              "ResBookDesigCode": "K",
              "RPH": "11",
              "AggregatedContent": false,
              "AggregatedContentSpecified": true
            },
            {
              "Availability": "7",
              "BrandID": null,
              "ResBookDesigCode": "L",
              "RPH": "12",
              "AggregatedContent": false,
              "AggregatedContentSpecified": true
            },
            {
              "Availability": "7",
              "BrandID": null,
              "ResBookDesigCode": "Q",
              "RPH": "13",
              "AggregatedContent": false,
              "AggregatedContentSpecified": true
            },
            {
              "Availability": "7",
              "BrandID": null,
              "ResBookDesigCode": "N",
              "RPH": "14",
              "AggregatedContent": false,
              "AggregatedContentSpecified": true
            },
            {
              "Availability": "7",
              "BrandID": null,
              "ResBookDesigCode": "R",
              "RPH": "15",
              "AggregatedContent": false,
              "AggregatedContentSpecified": true
            },
            {
              "Availability": "7",
              "BrandID": null,
              "ResBookDesigCode": "T",
              "RPH": "16",
              "AggregatedContent": false,
              "AggregatedContentSpecified": true
            },
            {
              "Availability": "7",
              "BrandID": null,
              "ResBookDesigCode": "E",
              "RPH": "17",
              "AggregatedContent": false,
              "AggregatedContentSpecified": true
            },
            {
              "Availability": "0",
              "BrandID": null,
              "ResBookDesigCode": "A",
              "RPH": "18",
              "AggregatedContent": false,
              "AggregatedContentSpecified": true
            },
            {
              "Availability": "7",
              "BrandID": null,
              "ResBookDesigCode": "P",
              "RPH": "19",
              "AggregatedContent": false,
              "AggregatedContentSpecified": true
            },
            {
              "Availability": "3",
              "BrandID": null,
              "ResBookDesigCode": "X",
              "RPH": "20",
              "AggregatedContent": false,
              "AggregatedContentSpecified": true
            },
            {
              "Availability": "0",
              "BrandID": null,
              "ResBookDesigCode": "V",
              "RPH": "21",
              "AggregatedContent": false,
              "AggregatedContentSpecified": true
            }
          ],
          "DaysOfOperation": {
            "OperationSchedule": {
              "OperationTimes": {
                "OperationTime": {
                  "Fri": true,
                  "FriSpecified": true,
                  "Mon": true,
                  "MonSpecified": true,
                  "Sat": true,
                  "SatSpecified": true,
                  "Sun": true,
                  "SunSpecified": true,
                  "Thur": true,
                  "ThurSpecified": true,
                  "Tue": true,
                  "TueSpecified": true,
                  "Weds": true,
                  "WedsSpecified": true
                }
              }
            }
          },
          "DestinationLocation": {
            "LocationCode": "SGN"
          },
          "DisclosureAirline": null,
          "Equipment": {
            "AirEquipType": "359"
          },
          "FlightDetails": {
            "Text": null,
            "Canceled": false,
            "CanceledSpecified": true,
            "Charter": false,
            "CharterSpecified": true,
            "CodeshareBlockDisplay": null,
            "DiscontinueDate": null,
            "EffectiveDate": null,
            "GroundTime": "0",
            "TotalTravelTime": "135",
            "TrafficRestrictionCode": null
          },
          "MarketingAirline": {
            "Code": "VN",
            "FlightNumber": "209",
            "ParticipationLevel": null
          },
          "Meal": [
            {
              "MealCode": "S"
            }
          ],
          "OperatingAirline": null,
          "OriginLocation": {
            "LocationCode": "HAN"
          },
          "ArrivalDateTime": "08-25T11:15",
          "ConnectionInd": null,
          "DepartureDateTime": "08-25T09:00",
          "DOT_Ind": "N",
          "eTicket": true,
          "eTicketSpecified": true,
          "FlightNumber": "209",
          "OnTimeInd": null,
          "RPH": "6",
          "SmokingAllowed": false,
          "SmokingAllowedSpecified": true,
          "StopQuantity": "0"
        }
      ],
      "RPH": "6"
    },
    {
      "FlightSegment": [
        {
          "BookingClassAvail": [
            {
              "Availability": "7",
              "BrandID": null,
              "ResBookDesigCode": "J",
              "RPH": "1",
              "AggregatedContent": false,
              "AggregatedContentSpecified": true
            },
            {
              "Availability": "7",
              "BrandID": null,
              "ResBookDesigCode": "C",
              "RPH": "2",
              "AggregatedContent": false,
              "AggregatedContentSpecified": true
            },
            {
              "Availability": "7",
              "BrandID": null,
              "ResBookDesigCode": "D",
              "RPH": "3",
              "AggregatedContent": false,
              "AggregatedContentSpecified": true
            },
            {
              "Availability": "0",
              "BrandID": null,
              "ResBookDesigCode": "I",
              "RPH": "4",
              "AggregatedContent": false,
              "AggregatedContentSpecified": true
            },
            {
              "Availability": "4",
              "BrandID": null,
              "ResBookDesigCode": "O",
              "RPH": "5",
              "AggregatedContent": false,
              "AggregatedContentSpecified": true
            },
            {
              "Availability": "7",
              "BrandID": null,
              "ResBookDesigCode": "Y",
              "RPH": "6",
              "AggregatedContent": false,
              "AggregatedContentSpecified": true
            },
            {
              "Availability": "7",
              "BrandID": null,
              "ResBookDesigCode": "B",
              "RPH": "7",
              "AggregatedContent": false,
              "AggregatedContentSpecified": true
            },
            {
              "Availability": "7",
              "BrandID": null,
              "ResBookDesigCode": "M",
              "RPH": "8",
              "AggregatedContent": false,
              "AggregatedContentSpecified": true
            },
            {
              "Availability": "7",
              "BrandID": null,
              "ResBookDesigCode": "S",
              "RPH": "9",
              "AggregatedContent": false,
              "AggregatedContentSpecified": true
            },
            {
              "Availability": "7",
              "BrandID": null,
              "ResBookDesigCode": "H",
              "RPH": "10",
              "AggregatedContent": false,
              "AggregatedContentSpecified": true
            },
            {
              "Availability": "7",
              "BrandID": null,
              "ResBookDesigCode": "K",
              "RPH": "11",
              "AggregatedContent": false,
              "AggregatedContentSpecified": true
            },
            {
              "Availability": "7",
              "BrandID": null,
              "ResBookDesigCode": "L",
              "RPH": "12",
              "AggregatedContent": false,
              "AggregatedContentSpecified": true
            },
            {
              "Availability": "7",
              "BrandID": null,
              "ResBookDesigCode": "Q",
              "RPH": "13",
              "AggregatedContent": false,
              "AggregatedContentSpecified": true
            },
            {
              "Availability": "7",
              "BrandID": null,
              "ResBookDesigCode": "N",
              "RPH": "14",
              "AggregatedContent": false,
              "AggregatedContentSpecified": true
            },
            {
              "Availability": "7",
              "BrandID": null,
              "ResBookDesigCode": "R",
              "RPH": "15",
              "AggregatedContent": false,
              "AggregatedContentSpecified": true
            },
            {
              "Availability": "7",
              "BrandID": null,
              "ResBookDesigCode": "T",
              "RPH": "16",
              "AggregatedContent": false,
              "AggregatedContentSpecified": true
            },
            {
              "Availability": "7",
              "BrandID": null,
              "ResBookDesigCode": "E",
              "RPH": "17",
              "AggregatedContent": false,
              "AggregatedContentSpecified": true
            },
            {
              "Availability": "0",
              "BrandID": null,
              "ResBookDesigCode": "A",
              "RPH": "18",
              "AggregatedContent": false,
              "AggregatedContentSpecified": true
            },
            {
              "Availability": "7",
              "BrandID": null,
              "ResBookDesigCode": "P",
              "RPH": "19",
              "AggregatedContent": false,
              "AggregatedContentSpecified": true
            },
            {
              "Availability": "2",
              "BrandID": null,
              "ResBookDesigCode": "X",
              "RPH": "20",
              "AggregatedContent": false,
              "AggregatedContentSpecified": true
            },
            {
              "Availability": "0",
              "BrandID": null,
              "ResBookDesigCode": "V",
              "RPH": "21",
              "AggregatedContent": false,
              "AggregatedContentSpecified": true
            }
          ],
          "DaysOfOperation": {
            "OperationSchedule": {
              "OperationTimes": {
                "OperationTime": {
                  "Fri": true,
                  "FriSpecified": true,
                  "Mon": true,
                  "MonSpecified": true,
                  "Sat": true,
                  "SatSpecified": true,
                  "Sun": true,
                  "SunSpecified": true,
                  "Thur": true,
                  "ThurSpecified": true,
                  "Tue": true,
                  "TueSpecified": true,
                  "Weds": true,
                  "WedsSpecified": true
                }
              }
            }
          },
          "DestinationLocation": {
            "LocationCode": "SGN"
          },
          "DisclosureAirline": null,
          "Equipment": {
            "AirEquipType": "787"
          },
          "FlightDetails": {
            "Text": null,
            "Canceled": false,
            "CanceledSpecified": true,
            "Charter": false,
            "CharterSpecified": true,
            "CodeshareBlockDisplay": null,
            "DiscontinueDate": null,
            "EffectiveDate": null,
            "GroundTime": "0",
            "TotalTravelTime": "135",
            "TrafficRestrictionCode": null
          },
          "MarketingAirline": {
            "Code": "VN",
            "FlightNumber": "251",
            "ParticipationLevel": null
          },
          "Meal": [
            {
              "MealCode": "S"
            }
          ],
          "OperatingAirline": null,
          "OriginLocation": {
            "LocationCode": "HAN"
          },
          "ArrivalDateTime": "08-25T12:15",
          "ConnectionInd": null,
          "DepartureDateTime": "08-25T10:00",
          "DOT_Ind": "N",
          "eTicket": true,
          "eTicketSpecified": true,
          "FlightNumber": "251",
          "OnTimeInd": null,
          "RPH": "7",
          "SmokingAllowed": false,
          "SmokingAllowedSpecified": true,
          "StopQuantity": "0"
        }
      ],
      "RPH": "7"
    },
    {
      "FlightSegment": [
        {
          "BookingClassAvail": [
            {
              "Availability": "7",
              "BrandID": null,
              "ResBookDesigCode": "J",
              "RPH": "1",
              "AggregatedContent": false,
              "AggregatedContentSpecified": true
            },
            {
              "Availability": "7",
              "BrandID": null,
              "ResBookDesigCode": "C",
              "RPH": "2",
              "AggregatedContent": false,
              "AggregatedContentSpecified": true
            },
            {
              "Availability": "7",
              "BrandID": null,
              "ResBookDesigCode": "D",
              "RPH": "3",
              "AggregatedContent": false,
              "AggregatedContentSpecified": true
            },
            {
              "Availability": "0",
              "BrandID": null,
              "ResBookDesigCode": "I",
              "RPH": "4",
              "AggregatedContent": false,
              "AggregatedContentSpecified": true
            },
            {
              "Availability": "5",
              "BrandID": null,
              "ResBookDesigCode": "O",
              "RPH": "5",
              "AggregatedContent": false,
              "AggregatedContentSpecified": true
            },
            {
              "Availability": "7",
              "BrandID": null,
              "ResBookDesigCode": "Y",
              "RPH": "6",
              "AggregatedContent": false,
              "AggregatedContentSpecified": true
            },
            {
              "Availability": "7",
              "BrandID": null,
              "ResBookDesigCode": "B",
              "RPH": "7",
              "AggregatedContent": false,
              "AggregatedContentSpecified": true
            },
            {
              "Availability": "7",
              "BrandID": null,
              "ResBookDesigCode": "M",
              "RPH": "8",
              "AggregatedContent": false,
              "AggregatedContentSpecified": true
            },
            {
              "Availability": "7",
              "BrandID": null,
              "ResBookDesigCode": "S",
              "RPH": "9",
              "AggregatedContent": false,
              "AggregatedContentSpecified": true
            },
            {
              "Availability": "7",
              "BrandID": null,
              "ResBookDesigCode": "H",
              "RPH": "10",
              "AggregatedContent": false,
              "AggregatedContentSpecified": true
            },
            {
              "Availability": "7",
              "BrandID": null,
              "ResBookDesigCode": "K",
              "RPH": "11",
              "AggregatedContent": false,
              "AggregatedContentSpecified": true
            },
            {
              "Availability": "7",
              "BrandID": null,
              "ResBookDesigCode": "L",
              "RPH": "12",
              "AggregatedContent": false,
              "AggregatedContentSpecified": true
            },
            {
              "Availability": "7",
              "BrandID": null,
              "ResBookDesigCode": "Q",
              "RPH": "13",
              "AggregatedContent": false,
              "AggregatedContentSpecified": true
            },
            {
              "Availability": "7",
              "BrandID": null,
              "ResBookDesigCode": "N",
              "RPH": "14",
              "AggregatedContent": false,
              "AggregatedContentSpecified": true
            },
            {
              "Availability": "7",
              "BrandID": null,
              "ResBookDesigCode": "R",
              "RPH": "15",
              "AggregatedContent": false,
              "AggregatedContentSpecified": true
            },
            {
              "Availability": "7",
              "BrandID": null,
              "ResBookDesigCode": "T",
              "RPH": "16",
              "AggregatedContent": false,
              "AggregatedContentSpecified": true
            },
            {
              "Availability": "7",
              "BrandID": null,
              "ResBookDesigCode": "E",
              "RPH": "17",
              "AggregatedContent": false,
              "AggregatedContentSpecified": true
            },
            {
              "Availability": "0",
              "BrandID": null,
              "ResBookDesigCode": "A",
              "RPH": "18",
              "AggregatedContent": false,
              "AggregatedContentSpecified": true
            },
            {
              "Availability": "7",
              "BrandID": null,
              "ResBookDesigCode": "P",
              "RPH": "19",
              "AggregatedContent": false,
              "AggregatedContentSpecified": true
            },
            {
              "Availability": "3",
              "BrandID": null,
              "ResBookDesigCode": "X",
              "RPH": "20",
              "AggregatedContent": false,
              "AggregatedContentSpecified": true
            },
            {
              "Availability": "0",
              "BrandID": null,
              "ResBookDesigCode": "V",
              "RPH": "21",
              "AggregatedContent": false,
              "AggregatedContentSpecified": true
            }
          ],
          "DaysOfOperation": {
            "OperationSchedule": {
              "OperationTimes": {
                "OperationTime": {
                  "Fri": true,
                  "FriSpecified": true,
                  "Mon": true,
                  "MonSpecified": true,
                  "Sat": true,
                  "SatSpecified": true,
                  "Sun": true,
                  "SunSpecified": true,
                  "Thur": true,
                  "ThurSpecified": true,
                  "Tue": true,
                  "TueSpecified": true,
                  "Weds": true,
                  "WedsSpecified": true
                }
              }
            }
          },
          "DestinationLocation": {
            "LocationCode": "SGN"
          },
          "DisclosureAirline": null,
          "Equipment": {
            "AirEquipType": "359"
          },
          "FlightDetails": {
            "Text": null,
            "Canceled": false,
            "CanceledSpecified": true,
            "Charter": false,
            "CharterSpecified": true,
            "CodeshareBlockDisplay": null,
            "DiscontinueDate": null,
            "EffectiveDate": null,
            "GroundTime": "0",
            "TotalTravelTime": "135",
            "TrafficRestrictionCode": null
          },
          "MarketingAirline": {
            "Code": "VN",
            "FlightNumber": "253",
            "ParticipationLevel": null
          },
          "Meal": [
            {
              "MealCode": "S"
            }
          ],
          "OperatingAirline": null,
          "OriginLocation": {
            "LocationCode": "HAN"
          },
          "ArrivalDateTime": "08-25T12:45",
          "ConnectionInd": null,
          "DepartureDateTime": "08-25T10:30",
          "DOT_Ind": "N",
          "eTicket": true,
          "eTicketSpecified": true,
          "FlightNumber": "253",
          "OnTimeInd": null,
          "RPH": "8",
          "SmokingAllowed": false,
          "SmokingAllowedSpecified": true,
          "StopQuantity": "0"
        }
      ],
      "RPH": "8"
    },
    {
      "FlightSegment": [
        {
          "BookingClassAvail": [
            {
              "Availability": "7",
              "BrandID": null,
              "ResBookDesigCode": "J",
              "RPH": "1",
              "AggregatedContent": false,
              "AggregatedContentSpecified": true
            },
            {
              "Availability": "7",
              "BrandID": null,
              "ResBookDesigCode": "C",
              "RPH": "2",
              "AggregatedContent": false,
              "AggregatedContentSpecified": true
            },
            {
              "Availability": "7",
              "BrandID": null,
              "ResBookDesigCode": "D",
              "RPH": "3",
              "AggregatedContent": false,
              "AggregatedContentSpecified": true
            },
            {
              "Availability": "0",
              "BrandID": null,
              "ResBookDesigCode": "I",
              "RPH": "4",
              "AggregatedContent": false,
              "AggregatedContentSpecified": true
            },
            {
              "Availability": "5",
              "BrandID": null,
              "ResBookDesigCode": "O",
              "RPH": "5",
              "AggregatedContent": false,
              "AggregatedContentSpecified": true
            },
            {
              "Availability": "7",
              "BrandID": null,
              "ResBookDesigCode": "Y",
              "RPH": "6",
              "AggregatedContent": false,
              "AggregatedContentSpecified": true
            },
            {
              "Availability": "7",
              "BrandID": null,
              "ResBookDesigCode": "B",
              "RPH": "7",
              "AggregatedContent": false,
              "AggregatedContentSpecified": true
            },
            {
              "Availability": "7",
              "BrandID": null,
              "ResBookDesigCode": "M",
              "RPH": "8",
              "AggregatedContent": false,
              "AggregatedContentSpecified": true
            },
            {
              "Availability": "7",
              "BrandID": null,
              "ResBookDesigCode": "S",
              "RPH": "9",
              "AggregatedContent": false,
              "AggregatedContentSpecified": true
            },
            {
              "Availability": "7",
              "BrandID": null,
              "ResBookDesigCode": "H",
              "RPH": "10",
              "AggregatedContent": false,
              "AggregatedContentSpecified": true
            },
            {
              "Availability": "7",
              "BrandID": null,
              "ResBookDesigCode": "K",
              "RPH": "11",
              "AggregatedContent": false,
              "AggregatedContentSpecified": true
            },
            {
              "Availability": "7",
              "BrandID": null,
              "ResBookDesigCode": "L",
              "RPH": "12",
              "AggregatedContent": false,
              "AggregatedContentSpecified": true
            },
            {
              "Availability": "7",
              "BrandID": null,
              "ResBookDesigCode": "Q",
              "RPH": "13",
              "AggregatedContent": false,
              "AggregatedContentSpecified": true
            },
            {
              "Availability": "7",
              "BrandID": null,
              "ResBookDesigCode": "N",
              "RPH": "14",
              "AggregatedContent": false,
              "AggregatedContentSpecified": true
            },
            {
              "Availability": "7",
              "BrandID": null,
              "ResBookDesigCode": "R",
              "RPH": "15",
              "AggregatedContent": false,
              "AggregatedContentSpecified": true
            },
            {
              "Availability": "7",
              "BrandID": null,
              "ResBookDesigCode": "T",
              "RPH": "16",
              "AggregatedContent": false,
              "AggregatedContentSpecified": true
            },
            {
              "Availability": "7",
              "BrandID": null,
              "ResBookDesigCode": "E",
              "RPH": "17",
              "AggregatedContent": false,
              "AggregatedContentSpecified": true
            },
            {
              "Availability": "0",
              "BrandID": null,
              "ResBookDesigCode": "A",
              "RPH": "18",
              "AggregatedContent": false,
              "AggregatedContentSpecified": true
            },
            {
              "Availability": "7",
              "BrandID": null,
              "ResBookDesigCode": "P",
              "RPH": "19",
              "AggregatedContent": false,
              "AggregatedContentSpecified": true
            },
            {
              "Availability": "3",
              "BrandID": null,
              "ResBookDesigCode": "X",
              "RPH": "20",
              "AggregatedContent": false,
              "AggregatedContentSpecified": true
            },
            {
              "Availability": "0",
              "BrandID": null,
              "ResBookDesigCode": "V",
              "RPH": "21",
              "AggregatedContent": false,
              "AggregatedContentSpecified": true
            }
          ],
          "DaysOfOperation": {
            "OperationSchedule": {
              "OperationTimes": {
                "OperationTime": {
                  "Fri": false,
                  "FriSpecified": true,
                  "Mon": true,
                  "MonSpecified": true,
                  "Sat": true,
                  "SatSpecified": true,
                  "Sun": false,
                  "SunSpecified": true,
                  "Thur": true,
                  "ThurSpecified": true,
                  "Tue": true,
                  "TueSpecified": true,
                  "Weds": false,
                  "WedsSpecified": true
                }
              }
            }
          },
          "DestinationLocation": {
            "LocationCode": "SGN"
          },
          "DisclosureAirline": null,
          "Equipment": {
            "AirEquipType": "359"
          },
          "FlightDetails": {
            "Text": null,
            "Canceled": false,
            "CanceledSpecified": true,
            "Charter": false,
            "CharterSpecified": true,
            "CodeshareBlockDisplay": null,
            "DiscontinueDate": null,
            "EffectiveDate": null,
            "GroundTime": "0",
            "TotalTravelTime": "135",
            "TrafficRestrictionCode": null
          },
          "MarketingAirline": {
            "Code": "VN",
            "FlightNumber": "211",
            "ParticipationLevel": null
          },
          "Meal": [
            {
              "MealCode": "L"
            }
          ],
          "OperatingAirline": null,
          "OriginLocation": {
            "LocationCode": "HAN"
          },
          "ArrivalDateTime": "08-25T13:15",
          "ConnectionInd": null,
          "DepartureDateTime": "08-25T11:00",
          "DOT_Ind": "N",
          "eTicket": true,
          "eTicketSpecified": true,
          "FlightNumber": "211",
          "OnTimeInd": null,
          "RPH": "9",
          "SmokingAllowed": false,
          "SmokingAllowedSpecified": true,
          "StopQuantity": "0"
        }
      ],
      "RPH": "9"
    },
    {
      "FlightSegment": [
        {
          "BookingClassAvail": [
            {
              "Availability": "7",
              "BrandID": null,
              "ResBookDesigCode": "J",
              "RPH": "1",
              "AggregatedContent": false,
              "AggregatedContentSpecified": true
            },
            {
              "Availability": "7",
              "BrandID": null,
              "ResBookDesigCode": "C",
              "RPH": "2",
              "AggregatedContent": false,
              "AggregatedContentSpecified": true
            },
            {
              "Availability": "7",
              "BrandID": null,
              "ResBookDesigCode": "D",
              "RPH": "3",
              "AggregatedContent": false,
              "AggregatedContentSpecified": true
            },
            {
              "Availability": "0",
              "BrandID": null,
              "ResBookDesigCode": "I",
              "RPH": "4",
              "AggregatedContent": false,
              "AggregatedContentSpecified": true
            },
            {
              "Availability": "4",
              "BrandID": null,
              "ResBookDesigCode": "O",
              "RPH": "5",
              "AggregatedContent": false,
              "AggregatedContentSpecified": true
            },
            {
              "Availability": "7",
              "BrandID": null,
              "ResBookDesigCode": "Y",
              "RPH": "6",
              "AggregatedContent": false,
              "AggregatedContentSpecified": true
            },
            {
              "Availability": "7",
              "BrandID": null,
              "ResBookDesigCode": "B",
              "RPH": "7",
              "AggregatedContent": false,
              "AggregatedContentSpecified": true
            },
            {
              "Availability": "7",
              "BrandID": null,
              "ResBookDesigCode": "M",
              "RPH": "8",
              "AggregatedContent": false,
              "AggregatedContentSpecified": true
            },
            {
              "Availability": "7",
              "BrandID": null,
              "ResBookDesigCode": "S",
              "RPH": "9",
              "AggregatedContent": false,
              "AggregatedContentSpecified": true
            },
            {
              "Availability": "7",
              "BrandID": null,
              "ResBookDesigCode": "H",
              "RPH": "10",
              "AggregatedContent": false,
              "AggregatedContentSpecified": true
            },
            {
              "Availability": "7",
              "BrandID": null,
              "ResBookDesigCode": "K",
              "RPH": "11",
              "AggregatedContent": false,
              "AggregatedContentSpecified": true
            },
            {
              "Availability": "7",
              "BrandID": null,
              "ResBookDesigCode": "L",
              "RPH": "12",
              "AggregatedContent": false,
              "AggregatedContentSpecified": true
            },
            {
              "Availability": "7",
              "BrandID": null,
              "ResBookDesigCode": "Q",
              "RPH": "13",
              "AggregatedContent": false,
              "AggregatedContentSpecified": true
            },
            {
              "Availability": "7",
              "BrandID": null,
              "ResBookDesigCode": "N",
              "RPH": "14",
              "AggregatedContent": false,
              "AggregatedContentSpecified": true
            },
            {
              "Availability": "7",
              "BrandID": null,
              "ResBookDesigCode": "R",
              "RPH": "15",
              "AggregatedContent": false,
              "AggregatedContentSpecified": true
            },
            {
              "Availability": "7",
              "BrandID": null,
              "ResBookDesigCode": "T",
              "RPH": "16",
              "AggregatedContent": false,
              "AggregatedContentSpecified": true
            },
            {
              "Availability": "7",
              "BrandID": null,
              "ResBookDesigCode": "E",
              "RPH": "17",
              "AggregatedContent": false,
              "AggregatedContentSpecified": true
            },
            {
              "Availability": "0",
              "BrandID": null,
              "ResBookDesigCode": "A",
              "RPH": "18",
              "AggregatedContent": false,
              "AggregatedContentSpecified": true
            },
            {
              "Availability": "7",
              "BrandID": null,
              "ResBookDesigCode": "P",
              "RPH": "19",
              "AggregatedContent": false,
              "AggregatedContentSpecified": true
            },
            {
              "Availability": "3",
              "BrandID": null,
              "ResBookDesigCode": "X",
              "RPH": "20",
              "AggregatedContent": false,
              "AggregatedContentSpecified": true
            },
            {
              "Availability": "0",
              "BrandID": null,
              "ResBookDesigCode": "V",
              "RPH": "21",
              "AggregatedContent": false,
              "AggregatedContentSpecified": true
            }
          ],
          "DaysOfOperation": {
            "OperationSchedule": {
              "OperationTimes": {
                "OperationTime": {
                  "Fri": false,
                  "FriSpecified": true,
                  "Mon": true,
                  "MonSpecified": true,
                  "Sat": true,
                  "SatSpecified": true,
                  "Sun": true,
                  "SunSpecified": true,
                  "Thur": true,
                  "ThurSpecified": true,
                  "Tue": true,
                  "TueSpecified": true,
                  "Weds": true,
                  "WedsSpecified": true
                }
              }
            }
          },
          "DestinationLocation": {
            "LocationCode": "SGN"
          },
          "DisclosureAirline": null,
          "Equipment": {
            "AirEquipType": "787"
          },
          "FlightDetails": {
            "Text": null,
            "Canceled": false,
            "CanceledSpecified": true,
            "Charter": false,
            "CharterSpecified": true,
            "CodeshareBlockDisplay": null,
            "DiscontinueDate": null,
            "EffectiveDate": null,
            "GroundTime": "0",
            "TotalTravelTime": "135",
            "TrafficRestrictionCode": null
          },
          "MarketingAirline": {
            "Code": "VN",
            "FlightNumber": "257",
            "ParticipationLevel": null
          },
          "Meal": [
            {
              "MealCode": "L"
            }
          ],
          "OperatingAirline": null,
          "OriginLocation": {
            "LocationCode": "HAN"
          },
          "ArrivalDateTime": "08-25T14:15",
          "ConnectionInd": null,
          "DepartureDateTime": "08-25T12:00",
          "DOT_Ind": "N",
          "eTicket": true,
          "eTicketSpecified": true,
          "FlightNumber": "257",
          "OnTimeInd": null,
          "RPH": "10",
          "SmokingAllowed": false,
          "SmokingAllowedSpecified": true,
          "StopQuantity": "0"
        }
      ],
      "RPH": "10"
    },
    {
      "FlightSegment": [
        {
          "BookingClassAvail": [
            {
              "Availability": "7",
              "BrandID": null,
              "ResBookDesigCode": "J",
              "RPH": "1",
              "AggregatedContent": false,
              "AggregatedContentSpecified": true
            },
            {
              "Availability": "7",
              "BrandID": null,
              "ResBookDesigCode": "C",
              "RPH": "2",
              "AggregatedContent": false,
              "AggregatedContentSpecified": true
            },
            {
              "Availability": "7",
              "BrandID": null,
              "ResBookDesigCode": "D",
              "RPH": "3",
              "AggregatedContent": false,
              "AggregatedContentSpecified": true
            },
            {
              "Availability": "0",
              "BrandID": null,
              "ResBookDesigCode": "I",
              "RPH": "4",
              "AggregatedContent": false,
              "AggregatedContentSpecified": true
            },
            {
              "Availability": "5",
              "BrandID": null,
              "ResBookDesigCode": "O",
              "RPH": "5",
              "AggregatedContent": false,
              "AggregatedContentSpecified": true
            },
            {
              "Availability": "7",
              "BrandID": null,
              "ResBookDesigCode": "Y",
              "RPH": "6",
              "AggregatedContent": false,
              "AggregatedContentSpecified": true
            },
            {
              "Availability": "7",
              "BrandID": null,
              "ResBookDesigCode": "B",
              "RPH": "7",
              "AggregatedContent": false,
              "AggregatedContentSpecified": true
            },
            {
              "Availability": "7",
              "BrandID": null,
              "ResBookDesigCode": "M",
              "RPH": "8",
              "AggregatedContent": false,
              "AggregatedContentSpecified": true
            },
            {
              "Availability": "7",
              "BrandID": null,
              "ResBookDesigCode": "S",
              "RPH": "9",
              "AggregatedContent": false,
              "AggregatedContentSpecified": true
            },
            {
              "Availability": "7",
              "BrandID": null,
              "ResBookDesigCode": "H",
              "RPH": "10",
              "AggregatedContent": false,
              "AggregatedContentSpecified": true
            },
            {
              "Availability": "7",
              "BrandID": null,
              "ResBookDesigCode": "K",
              "RPH": "11",
              "AggregatedContent": false,
              "AggregatedContentSpecified": true
            },
            {
              "Availability": "7",
              "BrandID": null,
              "ResBookDesigCode": "L",
              "RPH": "12",
              "AggregatedContent": false,
              "AggregatedContentSpecified": true
            },
            {
              "Availability": "7",
              "BrandID": null,
              "ResBookDesigCode": "Q",
              "RPH": "13",
              "AggregatedContent": false,
              "AggregatedContentSpecified": true
            },
            {
              "Availability": "7",
              "BrandID": null,
              "ResBookDesigCode": "N",
              "RPH": "14",
              "AggregatedContent": false,
              "AggregatedContentSpecified": true
            },
            {
              "Availability": "7",
              "BrandID": null,
              "ResBookDesigCode": "R",
              "RPH": "15",
              "AggregatedContent": false,
              "AggregatedContentSpecified": true
            },
            {
              "Availability": "7",
              "BrandID": null,
              "ResBookDesigCode": "T",
              "RPH": "16",
              "AggregatedContent": false,
              "AggregatedContentSpecified": true
            },
            {
              "Availability": "7",
              "BrandID": null,
              "ResBookDesigCode": "E",
              "RPH": "17",
              "AggregatedContent": false,
              "AggregatedContentSpecified": true
            },
            {
              "Availability": "0",
              "BrandID": null,
              "ResBookDesigCode": "A",
              "RPH": "18",
              "AggregatedContent": false,
              "AggregatedContentSpecified": true
            },
            {
              "Availability": "7",
              "BrandID": null,
              "ResBookDesigCode": "P",
              "RPH": "19",
              "AggregatedContent": false,
              "AggregatedContentSpecified": true
            },
            {
              "Availability": "3",
              "BrandID": null,
              "ResBookDesigCode": "X",
              "RPH": "20",
              "AggregatedContent": false,
              "AggregatedContentSpecified": true
            },
            {
              "Availability": "0",
              "BrandID": null,
              "ResBookDesigCode": "V",
              "RPH": "21",
              "AggregatedContent": false,
              "AggregatedContentSpecified": true
            }
          ],
          "DaysOfOperation": {
            "OperationSchedule": {
              "OperationTimes": {
                "OperationTime": {
                  "Fri": true,
                  "FriSpecified": true,
                  "Mon": true,
                  "MonSpecified": true,
                  "Sat": true,
                  "SatSpecified": true,
                  "Sun": true,
                  "SunSpecified": true,
                  "Thur": true,
                  "ThurSpecified": true,
                  "Tue": true,
                  "TueSpecified": true,
                  "Weds": true,
                  "WedsSpecified": true
                }
              }
            }
          },
          "DestinationLocation": {
            "LocationCode": "SGN"
          },
          "DisclosureAirline": null,
          "Equipment": {
            "AirEquipType": "787"
          },
          "FlightDetails": {
            "Text": null,
            "Canceled": false,
            "CanceledSpecified": true,
            "Charter": false,
            "CharterSpecified": true,
            "CodeshareBlockDisplay": null,
            "DiscontinueDate": null,
            "EffectiveDate": null,
            "GroundTime": "0",
            "TotalTravelTime": "135",
            "TrafficRestrictionCode": null
          },
          "MarketingAirline": {
            "Code": "VN",
            "FlightNumber": "213",
            "ParticipationLevel": null
          },
          "Meal": [
            {
              "MealCode": "L"
            }
          ],
          "OperatingAirline": null,
          "OriginLocation": {
            "LocationCode": "HAN"
          },
          "ArrivalDateTime": "08-25T15:15",
          "ConnectionInd": null,
          "DepartureDateTime": "08-25T13:00",
          "DOT_Ind": "N",
          "eTicket": true,
          "eTicketSpecified": true,
          "FlightNumber": "213",
          "OnTimeInd": null,
          "RPH": "11",
          "SmokingAllowed": false,
          "SmokingAllowedSpecified": true,
          "StopQuantity": "0"
        }
      ],
      "RPH": "11"
    },
    {
      "FlightSegment": [
        {
          "BookingClassAvail": [
            {
              "Availability": "7",
              "BrandID": null,
              "ResBookDesigCode": "J",
              "RPH": "1",
              "AggregatedContent": false,
              "AggregatedContentSpecified": true
            },
            {
              "Availability": "7",
              "BrandID": null,
              "ResBookDesigCode": "C",
              "RPH": "2",
              "AggregatedContent": false,
              "AggregatedContentSpecified": true
            },
            {
              "Availability": "7",
              "BrandID": null,
              "ResBookDesigCode": "D",
              "RPH": "3",
              "AggregatedContent": false,
              "AggregatedContentSpecified": true
            },
            {
              "Availability": "0",
              "BrandID": null,
              "ResBookDesigCode": "I",
              "RPH": "4",
              "AggregatedContent": false,
              "AggregatedContentSpecified": true
            },
            {
              "Availability": "5",
              "BrandID": null,
              "ResBookDesigCode": "O",
              "RPH": "5",
              "AggregatedContent": false,
              "AggregatedContentSpecified": true
            },
            {
              "Availability": "7",
              "BrandID": null,
              "ResBookDesigCode": "Y",
              "RPH": "6",
              "AggregatedContent": false,
              "AggregatedContentSpecified": true
            },
            {
              "Availability": "7",
              "BrandID": null,
              "ResBookDesigCode": "B",
              "RPH": "7",
              "AggregatedContent": false,
              "AggregatedContentSpecified": true
            },
            {
              "Availability": "7",
              "BrandID": null,
              "ResBookDesigCode": "M",
              "RPH": "8",
              "AggregatedContent": false,
              "AggregatedContentSpecified": true
            },
            {
              "Availability": "7",
              "BrandID": null,
              "ResBookDesigCode": "S",
              "RPH": "9",
              "AggregatedContent": false,
              "AggregatedContentSpecified": true
            },
            {
              "Availability": "7",
              "BrandID": null,
              "ResBookDesigCode": "H",
              "RPH": "10",
              "AggregatedContent": false,
              "AggregatedContentSpecified": true
            },
            {
              "Availability": "7",
              "BrandID": null,
              "ResBookDesigCode": "K",
              "RPH": "11",
              "AggregatedContent": false,
              "AggregatedContentSpecified": true
            },
            {
              "Availability": "7",
              "BrandID": null,
              "ResBookDesigCode": "L",
              "RPH": "12",
              "AggregatedContent": false,
              "AggregatedContentSpecified": true
            },
            {
              "Availability": "7",
              "BrandID": null,
              "ResBookDesigCode": "Q",
              "RPH": "13",
              "AggregatedContent": false,
              "AggregatedContentSpecified": true
            },
            {
              "Availability": "7",
              "BrandID": null,
              "ResBookDesigCode": "N",
              "RPH": "14",
              "AggregatedContent": false,
              "AggregatedContentSpecified": true
            },
            {
              "Availability": "7",
              "BrandID": null,
              "ResBookDesigCode": "R",
              "RPH": "15",
              "AggregatedContent": false,
              "AggregatedContentSpecified": true
            },
            {
              "Availability": "7",
              "BrandID": null,
              "ResBookDesigCode": "T",
              "RPH": "16",
              "AggregatedContent": false,
              "AggregatedContentSpecified": true
            },
            {
              "Availability": "7",
              "BrandID": null,
              "ResBookDesigCode": "E",
              "RPH": "17",
              "AggregatedContent": false,
              "AggregatedContentSpecified": true
            },
            {
              "Availability": "0",
              "BrandID": null,
              "ResBookDesigCode": "A",
              "RPH": "18",
              "AggregatedContent": false,
              "AggregatedContentSpecified": true
            },
            {
              "Availability": "7",
              "BrandID": null,
              "ResBookDesigCode": "P",
              "RPH": "19",
              "AggregatedContent": false,
              "AggregatedContentSpecified": true
            },
            {
              "Availability": "3",
              "BrandID": null,
              "ResBookDesigCode": "X",
              "RPH": "20",
              "AggregatedContent": false,
              "AggregatedContentSpecified": true
            },
            {
              "Availability": "0",
              "BrandID": null,
              "ResBookDesigCode": "V",
              "RPH": "21",
              "AggregatedContent": false,
              "AggregatedContentSpecified": true
            }
          ],
          "DaysOfOperation": {
            "OperationSchedule": {
              "OperationTimes": {
                "OperationTime": {
                  "Fri": true,
                  "FriSpecified": true,
                  "Mon": true,
                  "MonSpecified": true,
                  "Sat": true,
                  "SatSpecified": true,
                  "Sun": true,
                  "SunSpecified": true,
                  "Thur": true,
                  "ThurSpecified": true,
                  "Tue": true,
                  "TueSpecified": true,
                  "Weds": true,
                  "WedsSpecified": true
                }
              }
            }
          },
          "DestinationLocation": {
            "LocationCode": "SGN"
          },
          "DisclosureAirline": null,
          "Equipment": {
            "AirEquipType": "787"
          },
          "FlightDetails": {
            "Text": null,
            "Canceled": false,
            "CanceledSpecified": true,
            "Charter": false,
            "CharterSpecified": true,
            "CodeshareBlockDisplay": null,
            "DiscontinueDate": null,
            "EffectiveDate": null,
            "GroundTime": "0",
            "TotalTravelTime": "135",
            "TrafficRestrictionCode": null
          },
          "MarketingAirline": {
            "Code": "VN",
            "FlightNumber": "263",
            "ParticipationLevel": null
          },
          "Meal": [
            {
              "MealCode": "S"
            }
          ],
          "OperatingAirline": null,
          "OriginLocation": {
            "LocationCode": "HAN"
          },
          "ArrivalDateTime": "08-25T16:15",
          "ConnectionInd": null,
          "DepartureDateTime": "08-25T14:00",
          "DOT_Ind": "N",
          "eTicket": true,
          "eTicketSpecified": true,
          "FlightNumber": "263",
          "OnTimeInd": null,
          "RPH": "12",
          "SmokingAllowed": false,
          "SmokingAllowedSpecified": true,
          "StopQuantity": "0"
        }
      ],
      "RPH": "12"
    }
  ]
}
